{
	"info": {
		"_postman_id": "53cc8655-8ba9-4ed2-a109-4b0d98061c60",
		"name": "Express_postgre_API_Rifqi Apriansyah",
		"schema": "https://schema.getpostman.com/json/collection/v2.1.0/collection.json",
		"_exporter_id": "46876291",
		"_collection_link": "https://rifqiapriansyah.postman.co/workspace/68d457f5-5d79-413d-8bfa-c55dbafaa51b/collection/46876291-53cc8655-8ba9-4ed2-a109-4b0d98061c60?action=share&source=collection_link&creator=46876291"
	},
	"item": [
		{
			"name": "/api/users",
			"request": {
				"method": "POST",
				"header": [],
				"body": {
					"mode": "raw",
					"raw": "{\r\n  \"name\": \"Rifqi\",\r\n  \"email\": \"rifqi@example.com\"\r\n}\r\n",
					"options": {
						"raw": {
							"language": "json"
						}
					}
				},
				"url": {
					"raw": "http://localhost:3000/api/users",
					"protocol": "http",
					"host": [
						"localhost"
					],
					"port": "3000",
					"path": [
						"api",
						"users"
					]
				}
			},
			"response": []
		},
		{
			"name": "/api/books",
			"protocolProfileBehavior": {
				"disableBodyPruning": true
			},
			"request": {
				"method": "GET",
				"header": [],
				"body": {
					"mode": "raw",
					"raw": "",
					"options": {
						"raw": {
							"language": "json"
						}
					}
				},
				"url": {
					"raw": "http://localhost:3000/api/books",
					"protocol": "http",
					"host": [
						"localhost"
					],
					"port": "3000",
					"path": [
						"api",
						"books"
					]
				}
			},
			"response": []
		},
		{
			"name": "/api/books",
			"request": {
				"method": "POST",
				"header": [],
				"body": {
					"mode": "raw",
					"raw": "{\r\n  \"title\": \"Clean Architecture\",\r\n  \"author\": \"Robert C. Martin\",\r\n  \"userId\": 1\r\n}\r\n",
					"options": {
						"raw": {
							"language": "json"
						}
					}
				},
				"url": {
					"raw": "http://localhost:3000/api/books",
					"protocol": "http",
					"host": [
						"localhost"
					],
					"port": "3000",
					"path": [
						"api",
						"books"
					]
				}
			},
			"response": []
		},
		{
			"name": "New Request",
			"request": {
				"method": "GET",
				"header": []
			},
			"response": []
		}
	]
}